{
  "General": "ä¸€èˆ¬",
  "Tools": "å·¥å…·",
  "Capture": "æ•ç²",
  "Recording": "éŒ„éŸ³",
  "OCR": "å…‰å­¸å­—å…ƒè¾¨è­˜",
  "History": "歷史",
  "Capture History": "Capture History",
  "Uploads": "ä¸Šå‚³",
  "About": "é—œæ–¼",
  "Sound & Motion": "è²éŸ³èˆ‡å‹•ä½œ",
  "Language": "èªžè¨€",
  "Interface language": "ä»‹é¢èªžè¨€",
  "Auto (system language)": "è‡ªå‹•ï¼ˆç³»çµ±èªžè¨€ï¼‰",
  "Auto (interface/system language)": "è‡ªå‹•ï¼ˆä»‹é¢/ç³»çµ±èªžè¨€ï¼‰",
  "Auto-detect": "è‡ªå‹•åµæ¸¬",
  "English": "è‹±èªž",
  "Hebrew": "å¸Œä¼¯ä¾†æ–‡",
  "Mute capture sounds": "éœéŸ³æ•æ‰è²éŸ³",
  "Disable animations": "åœç”¨å‹•ç•«",
  "Sound pack": "è²éŸ³åŒ…",
  "Default": "預設",
  "Soft": "è»Ÿ",
  "Retro": "復古",
  "Search": "æœå°‹",
  "Show image search bar": "é¡¯ç¤ºåœ–ç‰‡æœå°‹æ¬„",
  "Auto-index images": "è‡ªå‹•ç´¢å¼•åœ–åƒ",
  }

